vector/code+testbench/design.v
module gray_to_binary(
    input [3:0] gray,
    output [3:0] binary
);
    assign binary[0] = gray[0];
    assign binary[1] = gray[0] ^ gray[1];
    assign binary[2] = gray[0] ^ gray[1] ^ gray[2];
    assign binary[3] = gray[0] ^ gray[1] ^ gray[2] ^ gray[3];
endmodule

vector/code+testbench/testbench.v
module testbench;
    reg [3:0] gray;
    wire [3:0] binary;

    gray_to_binary uut (
        .gray(gray),
        .binary(binary)
    );

    initial begin
        $dumpfile("dump.vcd");
        $dumpvars(0, testbench);

        gray = 4'b0000; 
        #100;
        gray = 4'b0001; 
        #100;
        gray = 4'b0010;
         #100;
        gray = 4'b0011; 
        #100;
        gray = 4'b0100;
         #100;
        gray = 4'b0101; 
        #100;
        gray = 4'b0110; 
        #100;
        gray = 4'b0111; 
        #100;
        gray = 4'b1000; 
        #100;
        gray = 4'b1001; 
        #100;
        gray = 4'b1010; 
        #100;
        gray = 4'b1011; 
        #100;
        gray = 4'b1100;
         #100;
        gray = 4'b1101; 
        #100;
        gray = 4'b1110; 
        #100;
        gray = 4'b1111; 
        #100;

        $finish;
    end
endmodule

vector/vcdfile_and_outfile/dump.vcd
$date
	Wed Aug 28 19:43:12 2024
$end
$version
	Icarus Verilog
$end
$timescale
	1s
$end
$scope module testbench $end
$var wire 4 ! binary [3:0] $end
$var reg 4 " gray [3:0] $end
$scope module uut $end
$var wire 4 # gray [3:0] $end
$var wire 4 $ binary [3:0] $end
$upscope $end
$upscope $end
$enddefinitions $end
#0
$dumpvars
b0 $
b0 #
b0 "
b0 !
$end
#100
b1111 !
b1111 $
b1 "
b1 #
#200
b1110 !
b1110 $
b10 "
b10 #
#300
b1 !
b1 $
b11 "
b11 #
#400
b1100 !
b1100 $
b100 "
b100 #
#500
b11 !
b11 $
b101 "
b101 #
#600
b10 !
b10 $
b110 "
b110 #
#700
b1101 !
b1101 $
b111 "
b111 #
#800
b1000 !
b1000 $
b1000 "
b1000 #
#900
b111 !
b111 $
b1001 "
b1001 #
#1000
b110 !
b110 $
b1010 "
b1010 #
#1100
b1001 !
b1001 $
b1011 "
b1011 #
#1200
b100 !
b100 $
b1100 "
b1100 #
#1300
b1011 !
b1011 $
b1101 "
b1101 #
#1400
b1010 !
b1010 $
b1110 "
b1110 #
#1500
b101 !
b101 $
b1111 "
b1111 #
